verifyaname/README.md
verifyaname/__init__.py
verifyaname/approval_token.py
verifyaname/helpers.py
verifyaname/verification_token.py
verifyaname-0.2.1.dist-info/METADATA
verifyaname-0.2.1.dist-info/WHEEL
verifyaname-0.2.1.dist-info/RECORD
