Metadata-Version: 2.1
Name: verifyaname
Version: 0.2.1
Summary: Aname verification library
License: Apache 2.0
Author: Fetch.AI Limited
Requires-Python: >=3.8,<3.12
Classifier: License :: Other/Proprietary License
Classifier: Programming Language :: Python :: 3
Classifier: Programming Language :: Python :: 3.8
Classifier: Programming Language :: Python :: 3.9
Classifier: Programming Language :: Python :: 3.10
Classifier: Programming Language :: Python :: 3.11
Requires-Dist: uagents
